db_facts/__init__.py
db_facts/aws_secrets_manager.py
db_facts/base64_jinja_context.py
db_facts/config.py
db_facts/config_yaml.py
db_facts/db_config.py
db_facts/db_facts_types.py
db_facts/db_info.py
db_facts/db_type.py
db_facts/env_jinja_context.py
db_facts/errors.py
db_facts/exports.py
db_facts/jinja_context.py
db_facts/list_db_names.py
db_facts/lpass.py
db_facts/main.py
db_facts/py.typed
db_facts/runner.py
db_facts/template.py
db_facts/util.py
db_facts/version.py
db_facts-5.1.1.data/scripts/db-facts
tests/__init__.py
tests/mock_dbcli_config.py
tests/test_config.py
tests/test_config_find_configs.py
tests/test_db_info.py
tests/test_db_info_errors.py
tests/test_db_info_json_script.py
tests/test_db_info_lastpass.py
tests/test_db_info_secrets_manager.py
tests/test_env_jinja_context.py
tests/test_jinja_context.py
tests/test_lpass.py
tests/test_multi_jinja_context.py
tests/test_nil_jinja_context.py
tests/test_runner_failure.py
tests/test_runner_success.py
tests/test_runner_success_config.py
tests/test_runner_success_json.py
tests/test_runner_success_list.py
tests/test_secrets_manager.py
db_facts-5.1.1.dist-info/LICENSE
db_facts-5.1.1.dist-info/METADATA
db_facts-5.1.1.dist-info/WHEEL
db_facts-5.1.1.dist-info/entry_points.txt
db_facts-5.1.1.dist-info/top_level.txt
db_facts-5.1.1.dist-info/RECORD
