Metadata-Version: 2.1
Name: db-facts
Version: 5.1.1
Summary: Database connection configuration manager
Home-page: UNKNOWN
Author: Vince Broz
Author-email: opensource@bluelabs.com
License: Apache Software License
Download-URL: https://github.com/bluelabsio/db-facts/archive/refs/tags/5.1.1.tar.gz
Platform: UNKNOWN
Classifier: Development Status :: 4 - Beta
Classifier: Intended Audience :: Developers
Classifier: Topic :: Database :: Front-Ends
Classifier: License :: OSI Approved :: Apache Software License
Classifier: Programming Language :: Python :: 3
Classifier: Programming Language :: Python :: 3.6
Classifier: Programming Language :: Python :: 3.7
Classifier: Programming Language :: Python :: 3.8
Requires-Dist: jinja2
Requires-Dist: pyyaml
Requires-Dist: boto3
